mauigpapi/__init__.py
mauigpapi/errors/__init__.py
mauigpapi/errors/base.py
mauigpapi/errors/mqtt.py
mauigpapi/errors/response.py
mauigpapi/errors/state.py
mauigpapi/http/__init__.py
mauigpapi/http/account.py
mauigpapi/http/api.py
mauigpapi/http/base.py
mauigpapi/http/challenge.py
mauigpapi/http/login.py
mauigpapi/http/thread.py
mauigpapi/http/upload.py
mauigpapi/http/user.py
mauigpapi/mqtt/__init__.py
mauigpapi/mqtt/conn.py
mauigpapi/mqtt/events.py
mauigpapi/mqtt/otclient.py
mauigpapi/mqtt/subscription.py
mauigpapi/mqtt/thrift/__init__.py
mauigpapi/mqtt/thrift/autospec.py
mauigpapi/mqtt/thrift/ig_objects.py
mauigpapi/mqtt/thrift/read.py
mauigpapi/mqtt/thrift/type.py
mauigpapi/mqtt/thrift/write.py
mauigpapi/scripts/__init__.py
mauigpapi/scripts/iglogin.py
mauigpapi/state/__init__.py
mauigpapi/state/application.py
mauigpapi/state/cookies.py
mauigpapi/state/device.py
mauigpapi/state/session.py
mauigpapi/state/state.py
mauigpapi/types/__init__.py
mauigpapi/types/account.py
mauigpapi/types/challenge.py
mauigpapi/types/direct_inbox.py
mauigpapi/types/error.py
mauigpapi/types/login.py
mauigpapi/types/mqtt.py
mauigpapi/types/qe.py
mauigpapi/types/thread.py
mauigpapi/types/thread_item.py
mauigpapi/types/upload.py
mauigpapi/types/user.py
mautrix_instagram/__init__.py
mautrix_instagram/__main__.py
mautrix_instagram/config.py
mautrix_instagram/example-config.yaml
mautrix_instagram/formatter.py
mautrix_instagram/get_version.py
mautrix_instagram/matrix.py
mautrix_instagram/portal.py
mautrix_instagram/puppet.py
mautrix_instagram/user.py
mautrix_instagram/version.py
mautrix_instagram/commands/__init__.py
mautrix_instagram/commands/auth.py
mautrix_instagram/commands/conn.py
mautrix_instagram/commands/misc.py
mautrix_instagram/commands/typehint.py
mautrix_instagram/db/__init__.py
mautrix_instagram/db/backfill_queue.py
mautrix_instagram/db/message.py
mautrix_instagram/db/portal.py
mautrix_instagram/db/puppet.py
mautrix_instagram/db/reaction.py
mautrix_instagram/db/user.py
mautrix_instagram-0.3.1.dist-info/LICENSE
mautrix_instagram-0.3.1.dist-info/METADATA
mautrix_instagram-0.3.1.dist-info/WHEEL
mautrix_instagram-0.3.1.dist-info/top_level.txt
mautrix_instagram-0.3.1.dist-info/RECORD
