Metadata-Version: 2.1
Name: mautrix-instagram
Version: 0.3.1
Summary: A Matrix-Instagram puppeting bridge.
Home-page: https://github.com/mautrix/instagram
Author: Tulir Asokan
Author-email: tulir@maunium.net
Project-URL: Changelog, https://github.com/mautrix/instagram/blob/master/CHANGELOG.md
Classifier: Development Status :: 4 - Beta
Classifier: License :: OSI Approved :: GNU Affero General Public License v3 or later (AGPLv3+)
Classifier: Topic :: Communications :: Chat
Classifier: Framework :: AsyncIO
Classifier: Programming Language :: Python
Classifier: Programming Language :: Python :: 3
Classifier: Programming Language :: Python :: 3.8
Classifier: Programming Language :: Python :: 3.9
Classifier: Programming Language :: Python :: 3.10
Requires-Python: ~=3.8
License-File: LICENSE
Requires-Dist: aiohttp (<4,>=3)
Requires-Dist: asyncpg (<0.29,>=0.20)
Requires-Dist: attrs (>=20.1)
Requires-Dist: commonmark (<0.10,>=0.8)
Requires-Dist: mautrix (<0.21,>=0.20.2)
Requires-Dist: paho-mqtt (<2,>=1.5)
Requires-Dist: pycryptodome (<4,>=3)
Requires-Dist: python-magic (<0.5,>=0.4)
Requires-Dist: ruamel.yaml (<0.18,>=0.15.35)
Requires-Dist: yarl (<2,>=1)
Provides-Extra: all
Requires-Dist: aiohttp-socks ; extra == 'all'
Requires-Dist: aiosqlite (<0.20,>=0.16) ; extra == 'all'
Requires-Dist: pillow (<11,>=10.0.1) ; extra == 'all'
Requires-Dist: prometheus-client (<0.18,>=0.6) ; extra == 'all'
Requires-Dist: pysocks ; extra == 'all'
Requires-Dist: python-olm (<4,>=3) ; extra == 'all'
Requires-Dist: unpaddedbase64 (<3,>=1) ; extra == 'all'
Provides-Extra: e2be
Requires-Dist: python-olm (<4,>=3) ; extra == 'e2be'
Requires-Dist: unpaddedbase64 (<3,>=1) ; extra == 'e2be'
Provides-Extra: imageconvert
Requires-Dist: pillow (<11,>=10.0.1) ; extra == 'imageconvert'
Provides-Extra: metrics
Requires-Dist: prometheus-client (<0.18,>=0.6) ; extra == 'metrics'
Provides-Extra: proxy
Requires-Dist: aiohttp-socks ; extra == 'proxy'
Requires-Dist: pysocks ; extra == 'proxy'
Provides-Extra: sqlite
Requires-Dist: aiosqlite (<0.20,>=0.16) ; extra == 'sqlite'
